CHANGELOG.txt
CONTRIBUTORS.txt
LICENSE
MANIFEST.in
README.md
requirements.txt
setup.py
django_twitter_auth_manager/__init__.py
django_twitter_auth_manager/admin.py
django_twitter_auth_manager/apps.py
django_twitter_auth_manager/models.py
django_twitter_auth_manager/urls.py
django_twitter_auth_manager/views.py
django_twitter_auth_manager.egg-info/PKG-INFO
django_twitter_auth_manager.egg-info/SOURCES.txt
django_twitter_auth_manager.egg-info/dependency_links.txt
django_twitter_auth_manager.egg-info/not-zip-safe
django_twitter_auth_manager.egg-info/top_level.txt
django_twitter_auth_manager/.github/dependabot.yml
django_twitter_auth_manager/migrations/0001_initial.py
django_twitter_auth_manager/migrations/__init__.py