Metadata-Version: 2.1
Name: django-twitter-auth-manager
Version: 1.0
Summary: Manage Twitter OAuth 2.0 Authorization Code Flow with PKCE (User Context) authentication by an Django app and store necessary token and refresh token for future uses.
Home-page: https://github.com/codesyntax/django-twitter-auth-manager
Author: Urtzi Odriozola (CodeSyntax http://codesyntax.com)
Author-email: uodriozola@codesyntax.com
Classifier: Programming Language :: Python :: 3
Classifier: Framework :: Django :: 1.11
Classifier: Framework :: Django :: 2.0
Classifier: Framework :: Django :: 3.0
Classifier: Framework :: Django :: 4.0
License-File: LICENSE
